mongodb_iam_connection_string/__init__.py
mongodb_iam_connection_string/cli.py
mongodb_iam_connection_string/exceptions.py
mongodb_iam_connection_string/mics.py
mongodb_iam_connection_string-1.0.1.dist-info/AUTHORS.rst
mongodb_iam_connection_string-1.0.1.dist-info/LICENSE
mongodb_iam_connection_string-1.0.1.dist-info/METADATA
mongodb_iam_connection_string-1.0.1.dist-info/WHEEL
mongodb_iam_connection_string-1.0.1.dist-info/entry_points.txt
mongodb_iam_connection_string-1.0.1.dist-info/top_level.txt
mongodb_iam_connection_string-1.0.1.dist-info/RECORD
