Metadata-Version: 2.1
Name: mongodb-iam-connection-string
Version: 1.0.1
Summary: A CLI and Python Library for configuration AWS IAM authentication with MongoDB URI connection strings.
Home-page: https://github.com/darrengruber/mongodb-iam-connection-string
Author: Darren Gruber
Author-email: dgruber@gmail.com
License: MIT license
Keywords: mongodb_iam_connection_string
Platform: UNKNOWN
Classifier: Development Status :: 2 - Pre-Alpha
Classifier: Intended Audience :: Developers
Classifier: License :: OSI Approved :: MIT License
Classifier: Natural Language :: English
Classifier: Programming Language :: Python :: 3
Classifier: Programming Language :: Python :: 3.5
Classifier: Programming Language :: Python :: 3.6
Classifier: Programming Language :: Python :: 3.7
Classifier: Programming Language :: Python :: 3.8
Requires-Python: >=3.5
Requires-Dist: boto3 (==1.14.52)
Requires-Dist: botocore (==1.17.52)
Requires-Dist: docopt (==0.6.2)
Requires-Dist: docutils (==0.15.2)
Requires-Dist: jmespath (==0.10.0)
Requires-Dist: python-dateutil (==2.8.1)
Requires-Dist: s3transfer (==0.3.3)
Requires-Dist: six (==1.15.0)
Requires-Dist: urllib3 (==1.25.10)
Requires-Dist: yurl (==1.0.0)
